[
    {
        "id": 1,
        "name": "Retro Sunglasses",
        "price": "$225.00",
        "images": [
            "images/Accessories/Retro-sunglasses_03.webp"
        ],
        "category": "Accessories",
        "description": "These Retro Sunglasses offer a vintage-inspired look with modern protection. Perfect for adding a stylish edge to any outfit."
    },
    {
        "id": 2,
        "name": "Miley Triangle Hair Scarf",
        "price": "$22.00",
        "images": [
            "images/Accessories/scrf1.webp",
            "images/Accessories/scrf2.webp",
            "images/Accessories/scrf3.webp"
        ],
        "category": "Accessories",
        "isTrending":true,
        "description": "The Miley Triangle Hair Scarf is a versatile accessory that can be styled in multiple ways. Made from soft, breathable fabric."
    },
    {
        "id": 13,
        "name": "Pride Sport Hip Pack",
        "price": "$39.00",
        "images": [
            "images/Bags/Pride-Sport-Hip-Pack-_04.webp",
            "images/Bags/Pride-Sport-Hip-Pack-_03.webp"
        ],
        "category": "Bags",
        "description": "The Pride Sport Hip Pack is perfect for carrying essentials hands-free. Features a vibrant design and multiple compartments for convenience."
    },
    {
        "id": 14,
        "name": "Dance Bag Nylon",
        "price": "$18.00",
        "images": [
            "images/Bags/p27-3_7e6d6ca6-5882-4c64-a166-577d894b0ac3.webp",
            "images/Bags/p27-1_1bcb95c6-a3da-4de5-b15e-ec08d4cb84b9.webp"
        ],
        "category": "Bags",
        "description": "The Dance Bag Nylon is lightweight and durable, ideal for carrying dance gear or gym essentials. Features a sleek design and ample storage space."
    }
]